smc3rateware/__init__.py
smc3rateware/config.py
smc3rateware/core.py
smc3rateware/definitions.py
smc3rateware/utils.py
smcrateware/__init__.py
smcrateware/config.py
smcrateware/core.py
smcrateware/definitions.py
smcrateware/utils.py
tests/__init__.py
tests/common.py
tests/test_data.py
tests/test_rating.py
smc3rateware-1.0.dist-info/LICENSE
smc3rateware-1.0.dist-info/METADATA
smc3rateware-1.0.dist-info/WHEEL
smc3rateware-1.0.dist-info/top_level.txt
smc3rateware-1.0.dist-info/RECORD
