Metadata-Version: 2.1
Name: smc3rateware
Version: 1.0
Summary: A python package for SCM3 Rateware integrations.
Home-page: https://github.com/NFI-Industries/python_SMCRateware
Author: Chris Pryer
Author-email: christophpryer@gmail.com
License: PUBLIC
Platform: UNKNOWN
